{
  "日": {
    "onyomi": [
      "ニチ",
      "ジツ"
    ],
    "kunyomi": [
      "ひ",
      "-び",
      "-か"
    ],
    "meaning": "day, sun, Japan, counter for days",
    "onyomiWords": [
      {
        "word": "同日",
        "reading": "どうじつ",
        "meaning": "the same day"
      },
      {
        "word": "前日",
        "reading": "ぜんじつ",
        "meaning": "previous day, day before"
      },
      {
        "word": "毎日 ",
        "reading": "まいにち",
        "meaning": "every day"
      },
      {
        "word": "日常 ",
        "reading": "にちじょう",
        "meaning": "ordinary, regular"
      }
    ],
    "kunyomiWords": [
      {
        "word": "記念日",
        "reading": "きねんび",
        "meaning": "anniversary, memorial day"
      }
    ],
    "specialReadings": [
      {
        "word": "今日",
        "reading": "きょう",
        "meaning": "today, this day"
      },
      {
        "word": "明日",
        "reading": "あした",
        "meaning": "tomorrow"
      },
      {
        "word": "昨日 ",
        "reading": "きのう",
        "meaning": "yesterday"
      }
    ],
    "examples": [
      {
        "sentence": "1. 毎日、日本語を勉強します。",
        "reading": "まいにち、にほんごをべんきょうします。",
        "romanji": "mainichi nihongo o benkyou shimasu.",
        "meaning": "I study Japanese everyday."
      },
      {
        "sentence": "2. ある日、私は彼に会った。",
        "reading": "あるひ、わたしはかれにあった。",
        "romanji": "aru hi, watashi wa kare ni atta.",
        "meaning": "One day I met him."
      },
      {
        "sentence": "3. 私は数日間休みます。",
        "reading": "わたしはすうじつかんやすみます。",
        "romanji": "watashi wa suujitsukan yasumimasu.",
        "meaning": "I'm going to take off a few days."
      }
    ]
  },
  "一": {
    "onyomi": [
      "イチ"
    ],
    "kunyomi": [
      "ひと(つ)"
    ],
    "meaning": "one",
    "onyomiWords": [
      {
        "word": "一日",
        "reading": "いちにち",
        "meaning": "one day"
      },
      {
        "word": "一番",
        "reading": "いちばん",
        "meaning": "#1; the best"
      },
      {
        "word": "世界一",
        "reading": "せかいいち",
        "meaning": "the best in the world"
      },
      {
        "word": "一日中",
        "reading": "いちにちちゅう",
        "meaning": "all day"
      },
      {
        "word": "一周 ",
        "reading": "いっしゅう",
        "meaning": "one lap"
      },
      {
        "word": "一個 ",
        "reading": "いっこ",
        "meaning": "one thing(counter)"
      }
    ],
    "kunyomiWords": [
      {
        "word": "一人",
        "reading": "ひとり",
        "meaning": "one person"
      },
      {
        "word": "一つ",
        "reading": "ひとつ",
        "meaning": "one thing (general counter)"
      }
    ],
    "specialReadings": [
      {
        "word": "一日",
        "reading": "ついたち",
        "meaning": "1st day of the month"
      }
    ],
    "examples": [
      {
        "sentence": "1. 一人で学校へ行きます。",
        "reading": "ひとりでがっこうへいきます。",
        "romanji": "hitori de gakkou he ikimasu.",
        "meaning": "I go to school alone."
      },
      {
        "sentence": "2. たい焼き一匹ください。",
        "reading": "たいやきいっぴきください。",
        "romanji": "taiyaki ippiki kudasai.",
        "meaning": "One taiyaki please."
      },
      {
        "sentence": "3. 一週間ずっと日本語を勉強しました。",
        "reading": "いっしゅうかんずっとにほんごをべんきょうしました。",
        "romanji": "isshuukan zutto nihongo o benkyou shimashita.",
        "meaning": "I studied Japanese all week long."
      }
    ]
  },
  "国": {
    "onyomi": [
      "コク"
    ],
    "kunyomi": [
      "くに"
    ],
    "meaning": "country",
    "onyomiWords": [
      {
        "word": "国王",
        "reading": "こくおう",
        "meaning": "King"
      },
      {
        "word": "韓国",
        "reading": "かんこく",
        "meaning": "South Korea"
      },
      {
        "word": "中国",
        "reading": "ちゅうごく",
        "meaning": "China"
      },
      {
        "word": "米国",
        "reading": "べいこく",
        "meaning": "America, USA"
      },
      {
        "word": "外国",
        "reading": "がいこく",
        "meaning": "foreign country"
      },
      {
        "word": "国際",
        "reading": "こくさい",
        "meaning": "international"
      },
      {
        "word": "外国人",
        "reading": "がいこくじん",
        "meaning": "foreigner, foreign citizen"
      }
    ],
    "kunyomiWords": [
      {
        "word": "国",
        "reading": "くに",
        "meaning": "country, state, region, national government"
      }
    ],
    "specialReadings": [],
    "examples": [
      {
        "sentence": "1. あなたはどこの国から来ましたか？",
        "reading": "あなたはどこのくにからきましたか？",
        "romanji": "anata wa doko no kuni kara kimashita ka?",
        "meaning": "What country did you come from?"
      },
      {
        "sentence": "2. 彼は外国に長年住んでいた。",
        "reading": "かれはがいこくにながねんすんでいた。",
        "romanji": "kare wa gaikoku ni naganen sundeita.",
        "meaning": "He lived abroad for many years."
      },
      {
        "sentence": "3. 私は米国から来ました。",
        "reading": "わたしはべいこくからきました。",
        "romanji": "watashi wa beikoku kara kimashita.",
        "meaning": "I came here from the USA."
      }
    ]
  },
  "人": {
    "onyomi": [
      "ジン",
      "ニン"
    ],
    "kunyomi": [
      "ひと"
    ],
    "meaning": "person",
    "onyomiWords": [
      {
        "word": "人気",
        "reading": "にんき",
        "meaning": "popularity, public favor, tone, nature"
      },
      {
        "word": "同人",
        "reading": "どうじん",
        "meaning": "same person, said person, the person in question"
      },
      {
        "word": "代人",
        "reading": "だいにん",
        "meaning": "substitute, deputy, proxy, representative, agent"
      },
      {
        "word": "証人",
        "reading": "しょうにん",
        "meaning": "witness"
      },
      {
        "word": "巨人",
        "reading": "きょじん",
        "meaning": "giant, great man"
      },
      {
        "word": "人間",
        "reading": "にんげん",
        "meaning": "human being, man"
      },
      {
        "word": "友人",
        "reading": "ゆうじん",
        "meaning": "friend"
      },
      {
        "word": "成人",
        "reading": "せいじん",
        "meaning": "adult"
      },
      {
        "word": "日本人",
        "reading": "にほんじん",
        "meaning": "Japanese people"
      }
    ],
    "kunyomiWords": [
      {
        "word": "人一倍",
        "reading": "ひといちばい",
        "meaning": "(much) more than others, exceedingly"
      },
      {
        "word": "いい人",
        "reading": "いいひと",
        "meaning": "good-natured person, good person, lover"
      },
      {
        "word": "恋人",
        "reading": "こいびと",  
        "meaning": "lover, sweetheart"
      }
    ],
    "specialReadings": [
        {
          "word": "大人",
          "reading": "おとな",
          "meaning": "adult"
        },
        {
          "word": "一人",
          "reading": "ひとり",
          "meaning": "alone; one person"
        }
    ],
    "examples": [
      {
        "sentence": "1. 私はアメリカ人です。",
        "reading": "わたしはあめりかじんです。",
        "romanji": "watashi wa amerikajin desu.",
        "meaning": "I am American."
      },
      {
        "sentence": "2. 私の兄は人気がある。",
        "reading": "わたしのあにはにんきがある。",
        "romanji": "watashi no ani wa ninki ga aru.",
        "meaning": "My older brother is popular."
      },
      {
        "sentence": "3. 君は僕のただ 1人の友人だ。",
        "reading": "きみはぼくのただひとりのゆうじんだ。",
        "romanji": "kimi wa boku no tada hitori no yuujin da.",
        "meaning": "You're my one and only true friend."
      }
    ]
  },
  "年": {
    "onyomi": [
      "ネン"
    ],
    "kunyomi": [
      "とし"
    ],
    "meaning": "year, counter for years",
    "onyomiWords": [
      {
        "word": "去年",
        "reading": "きょねん",
        "meaning": "last year"
      },
      {
        "word": "来年",
        "reading": "らいねん",
        "meaning": "next year"
      },
      {
        "word": "数年",
        "reading": "すうねん",
        "meaning": "several years"
      },
      {
        "word": "年中 ",
        "reading": "ねんじゅう",
        "meaning": "whole year"
      },
      {
        "word": "新年",
        "reading": "しんねん",
        "meaning": "New Year"
      },
      {
        "word": "学年",
        "reading": "がくねん",
        "meaning": "academic year"
      },
      {
        "word": "年収 ",
        "reading": "ねんしゅう",
        "meaning": "annual income"
      }
    ],
    "kunyomiWords": [
      {
        "word": "今年",
        "reading": "ことし",
        "meaning": "this year"
      },
      {
        "word": "一昨年",
        "reading": "おととし",
        "meaning": "year before last"
      },
      {
        "word": "年上 ",
        "reading": "としうえ",
        "meaning": "older, senior"
      },
      {
        "word": "毎年",
        "reading": "まいとし",
        "meaning": "every year, yearly"
      }
    ],
    "specialReadings": [],
    "examples": [
      {
        "sentence": "1. お年はいくつですか？",
        "reading": "おとしはいくつですか？",
        "romanji": "otoshi wa ikutsu desu ka?",
        "meaning": "How old are you?"
      },
      {
        "sentence": "2. 去年日本へ行きました。",
        "reading": "きょねんにほんへいきました。",
        "romanji": "kyonen nihon he ikimashita.",
        "meaning": "I went to Japan last year."
      },
      {
        "sentence": "3. 今年毎日ランニングをします。",
        "reading": "ことしまいにちらんにんぐをします。",
        "romanji": "kotoshi mainichi ranningu o shimasu.",
        "meaning": "I will go running every day this year."
      }
    ]
  },
  "大": {
    "onyomi": [
      "ダイ",
      "タイ"
    ],
    "kunyomi": [
      "おお(きい)"
    ],
    "meaning": "large, big",
    "onyomiWords": [
      {
        "word": "大好き",
        "reading": "だいすき",
        "meaning": "very likeable"
      },
      {
        "word": "大丈夫",
        "reading": "だいじょうぶ",
        "meaning": "safe, all right, okay"
      },
      {
        "word": "最大",
        "reading": "さいだい",
        "meaning": "biggest, greatest"
      },
      {
        "word": "大事",
        "reading": "だいじ",
        "meaning": "important, valuable"
      },
      {
        "word": "大切",
        "reading": "たいせつ",
        "meaning": "important, necessary"
      },
      {
        "word": "大統領",
        "reading": "だいとうりょう",
        "meaning": "president"
      }
    ],
    "kunyomiWords": [
      {
        "word": "大きい",
        "reading": "おおきい",
        "meaning": "big, large, great, loud, extensive, spacious, important"
      },
      {
        "word": "大通り",
        "reading": "おおどおり",
        "meaning": "main street"
      },
      {
        "word": "大盛",
        "reading": "おおもり",
        "meaning": "large size (food)"
      }
    ],
    "specialReadings": [],
    "examples": [
      {
        "sentence": "1. あなたのことが大好きだ。",
        "reading": "あなたのことがだいすきだ。",
        "romanji": "anata no koto ga daisuki da.",
        "meaning": "I love you! (or like you a lot)"
      },
      {
        "sentence": "2. このハンバーガーは大きいですね。",
        "reading": "このハンバーガーはおおきいですね。",
        "romanji": "kono hanbaagaa wa ookii desune.",
        "meaning": "This hamburger is huge."
      },
      {
        "sentence": "3. 来週アメリカの大使館に行きます。",
        "reading": "らいしゅうあめりかのたいしかんにいきます。",
        "romanji": "raishuu amerika no taishikan ni ikimasu.",
        "meaning": "I'm going to the American embassy next week."
      }
    ]
  },
  "十": {
    "onyomi": [
      "ジュウ"
    ],
    "kunyomi": [
      "とお",
      "と"
    ],
    "meaning": "ten, 10",
    "onyomiWords": [
      {
        "word": "十一 ",
        "reading": "じゅういち",
        "meaning": "eleven, 11, jack (playing card)"
      },
      {
        "word": "十月",
        "reading": "じゅうがつ",
        "meaning": "October"
      },
      {
        "word": "十分 ",
        "reading": "じゅうぶん",
        "meaning": "enough; sufficient; plenty; adequate; satisfactory"
      },
      {
        "word": "十代",
        "reading": "じゅうだい",
        "meaning": "the teens (10-19); teenage"
      }
    ],
    "kunyomiWords": [
      {
        "word": "十日",
        "reading": "とおか",
        "meaning": "the tenth day of the month, ten days"
      }
    ],
    "specialReadings": [
      {
        "word": "二十日",
        "reading": "はつか",
        "meaning": "20th day of the month"
      },
      {
        "word": "二十歳",
        "reading": "はたち",
        "meaning": "20 years old"
      }
    ],
    "examples": [
      {
        "sentence": "1. 今日は十四日です。",
        "reading": "きょうはじゅうよんにちです。",
        "romanji": "kyou wa juuyon nichi desu.",
        "meaning": "Today is the 14th."
      },
      {
        "sentence": "2. 来月二十歳になります。",
        "reading": "らいげつはたちになります。",
        "romanji": "raigetsu hatachi ni narimasu.",
        "meaning": "I turn 20 next month."
      },
      {
        "sentence": "3. 十月の天気が大好きです。",
        "reading": "じゅうがつのてんきがだいすきです。",
        "romanji": "juugatsu no tenki ga daisuki desu.",
        "meaning": "I love the weather in October."
      }
    ]
  },
  "二": {
    "onyomi": [
      "ニ",
      "ジ"
    ],
    "kunyomi": [
      "ふた(つ)"
    ],
    "meaning": "two, 2",
    "onyomiWords": [
      {
        "word": "十二",
        "reading": "じゅうに",
        "meaning": "twelve, 12, queen (playing card)"
      },
      {
        "word": "二月",
        "reading": "にがつ",
        "meaning": "February"
      },
      {
        "word": "二部",
        "reading": "にぶ",
        "meaning": "2nd part"
      },
      {
        "word": "二番",
        "reading": "にばん",
        "meaning": "second, number 2, runner-up"
      }
    ],
    "kunyomiWords": [
      {
        "word": "二人",
        "reading": "ふたり",
        "meaning": "two people"
      },
      {
        "word": "二重",
        "reading": "にじゅう",
        "meaning": "double, two-fold, two layers"
      },
      {
        "word": "二日酔い",
        "reading": "ふつかよい",
        "meaning": "hangover"
      }
    ],
    "specialReadings": [
       {
        "word": "二十日",
        "reading": "はつか",
        "meaning": "20th day of the month"
      }
    ],
    "examples": [
      {
        "sentence": "1. 水を二つください！",
        "reading": "みずをふたつください！",
        "romanji": "mizu o futatsu kudasai!",
        "meaning": "2 waters please!"
      },
      {
        "sentence": "2. 二月はとても寒いです。",
        "reading": "にがつはとてもさむいです。",
        "romanji": "ni gatsu wa totemo samui desu.",
        "meaning": "February is very cold."
      },
      {
        "sentence": "3. 私の誕生日は二月二十日です。",
        "reading": "わたしのたんじょうびはにがつはつかです。",
        "romanji": "watashi no tanjoubi wa ni gatsu hatsuka desu.",
        "meaning": "My birthday is February 20th."
      }
    ]
  },
  "本": {
    "onyomi": [
      "ホン"
    ],
    "kunyomi": [
      "もと"
    ],
    "meaning": "book, present, true, counter for long cylindrical things",
    "onyomiWords": [
      {
        "word": "本の",
        "reading": "ほんの",
        "meaning": "mere; only; just; slight"
      },
      {
        "word": "本気",
        "reading": "ほんきく",
        "meaning": "seriousness; earnestness; truth"
      },
      {
        "word": "本棚",
        "reading": "ほんだな",
        "meaning": "bookshelves; bookshelf; bookcase"
      },
      {
        "word": "本当",
        "reading": "ほんとう",
        "meaning": "truth; reality; actuality; fact"
      },
      {
        "word": "本位",
        "reading": "ほんい",
        "meaning": "standard, basis, principle"
      }
    ],
    "kunyomiWords": [
      {
        "word": "大本",
        "reading": "おおもと",
        "meaning": "root, origin, source, cause, basis, foundation"
      }
    ],
    "specialReadings": [],
    "examples": [
      {
        "sentence": "1. この本を読んだことがありますか？",
        "reading": "このほんをよんだことがありますか？",
        "romanji": "kono hon o yonda koto ga arimasu ka?",
        "meaning": "Have you ever read this book?"
      },
      {
        "sentence": "2. 来月日本に行きます。",
        "reading": "らいげつにほんにいきます。",
        "romanji": "raigetsu nihon ni ikimasu.",
        "meaning": "I will go to Japan next month."
      },
      {
        "sentence": "3. 本当のことを教えてください。",
        "reading": "ほんとうのことをおしえてください。",
        "romanji": "hontou no koto o oshiete kudasai.",
        "meaning": "Please tell me the truth."
      }
    ]
  },
  "中": {
    "onyomi": [
      "チュウ"
    ],
    "kunyomi": [
      "なか",
      "うち",
      "あた(る)"
    ],
    "meaning": "in, inside, middle, mean, center",
    "onyomiWords": [
      {
        "word": "中心",
        "reading": "ちゅうしん",
        "meaning": "center, heart"
      },
      {
        "word": "中学",
        "reading": "ちゅうがっこう",
        "meaning": "middle school"
      },
      {
        "word": "水中",
        "reading": "すいちゅう",
        "meaning": "underwater"
      },
      {
        "word": "中毒",
        "reading": "ちゅうどく",
        "meaning": "poisoning"
      }
    ],
    "kunyomiWords": [
      {
        "word": "真中",
        "reading": "まんなか",
        "meaning": "middle"
      },
       {
        "word": "夜中",
        "reading": "よなか",
        "meaning": "midnight"
      }
    ],
    "specialReadings": [],
    "examples": [
      {
        "sentence": "1. 中国に行ったことがありますか？",
        "reading": "ちゅうごくにいったことがありますか？",
        "romanji": "chuugoku ni itta koto ga arimasu ka?",
        "meaning": "Have you ever been to China before?"
      },
      {
        "sentence": "2. 今は家の中にいますよ。",
        "reading": "いまはいえのなかにいますよ。",
        "romanji": "ima wa ie no naka ni imasu yo.",
        "meaning": "I'm inside the house right now."
      },
      {
        "sentence": "3. 写真の中に何が見えますか？",
        "reading": "しゃしんのなかになにがみえますか？",
        "romanji": "shashin no naka ni nani ga miemasu ka?",
        "meaning": "What do you see in the picture?"
      }
    ]
  },
  "長": {
    "onyomi": [
      "チョウ"
    ],
    "kunyomi": [
      "なが(い)",
      "おさ"
    ],
    "meaning": "long, leader, superior, senior",
    "onyomiWords": [
      {
        "word": "長官",
        "reading": "ちょうかん",
        "meaning": "secretary (government), director, chief"
      },
      {
        "word": "医長",
        "reading": "いちょう",
        "meaning": "medical director, chief physician"
      },
      {
        "word": "成長",
        "reading": "せいちょう",
        "meaning": "growth, grow to adulthood"
      }
    ],
    "kunyomiWords": [
      {
        "word": "長居",
        "reading": "ながい",
        "meaning": "long visit, overstaying"
      }
    ],
    "specialReadings": [],
    "examples": [
      {
        "sentence": "1. 長い一日だった。",
        "reading": "ながいいちにちだった。",
        "romanji": "nagai ichinichi datta.",
        "meaning": "Today was a long day."
      },
      {
        "sentence": "2. 私たちは長い時間話しました。",
        "reading": "わたしたちはながいじかんはなしました。",
        "romanji": "watashitachi nagai jikan hanashimashita.",
        "meaning": "We talked for a long time."
      },
      {
        "sentence": "3. 私の部長はとてもやさしい人です。",
        "reading": "わたしのぶちょうはとてもやさしいひとです。",
        "romanji": "watashi no buchou wa totemo yasashii hito desu.",
        "meaning": "My manager is a very kind person."
      }
    ]
  },
  "出": {
    "onyomi": [
      "シュツ","スイ"
    ],
    "kunyomi": [
      "で(る)","だ(す)","い(でる)"
    ],
    "meaning": "exit, leave, go out",
    "onyomiWords": [
      {
        "word": "出血",
        "reading": "しゅっけつ",
        "meaning": "bleeding"
      },
      {
        "word": "出張",
        "reading": "しゅっちょう",
        "meaning": "business trip"
      },
      {
        "word": "出生 ",
        "reading": "しゅっせい",
        "meaning": "birth"
      }
    ],
    "kunyomiWords": [
      {
        "word": "出店",
        "reading": "でみせ",
        "meaning": "food stand"
      },
       {
        "word": "引出し",
        "reading": "ひきだし",
        "meaning": "drawer"
      },
      {
        "word": "出でる",
        "reading": "いでる",
        "meaning": "to go, to come"
      }
    ],
    "specialReadings": [],
    "examples": [
      {
        "sentence": "1. かれが出張に行く。",
        "reading": "かれがしゅっちょうにいく。",
        "romanji": "kare ga shuchcou ni iku.",
        "meaning": "He's going on a business trip."
      },
      {
        "sentence": "2. 出口はどちらですか。",
        "reading": "でぐちはどちらですか。。",
        "romanji": "deguchi wa dochira desu ka.",
        "meaning": "Where is the exit?"
      },
      {
        "sentence": "3. 会議に出席します。",
        "reading": "かいぎにしゅっせきします。",
        "romanji": "kaigi ni shusseki shimasu.",
        "meaning": "I will attend the meeting."
      }
    ]
  },
  "三": {
    "onyomi": [
      "サン"
    ],
    "kunyomi": [
      "み(つ)"
    ],
    "meaning": "three, 3",
    "onyomiWords": [
      {
        "word": "再三",
        "reading": "さいさん",
        "meaning": "again and again; repeatedly"
      },
      {
        "word": "三時",
        "reading": "さんじ",
        "meaning": "3 o'clock"
      },
      {
        "word": "三月",
        "reading": "さんがつ",
        "meaning": "March"
      }
    ],
    "kunyomiWords": [
      {
        "word": "三つ折り",
        "reading": "みつおり",
        "meaning": "threefold, folded in three"
      }
    ],
    "specialReadings": [
      {
        "word": "三味線",
        "reading": "しゃみせん",
        "meaning": "Shamisen"
      }
    ],
    "examples": [
      {
        "sentence": "1. 二、三分お待ちください。",
        "reading": "に、さんぷんおまちください。",
        "romanji": "ni, san pun o machi kudasai.",
        "meaning": "Please wait for a few minutes."
      },
      {
        "sentence": "2. 今年は三十歳になります。",
        "reading": "ことしはさんじゅうさいになります。",
        "romanji": "kotoshi wa sanjuu sai ni narimasu.",
        "meaning": "I turn 30 years old this year."
      },
      {
        "sentence": "3. 水を三つをください。",
        "reading": "みずをみつください。",
        "romanji": "mizu o mitsu kudasai.",
        "meaning": "3 waters please."
      }
    ]
  },
  "時": {
    "onyomi": [
      "ジ"
    ],
    "kunyomi": [
      "とき","-どき"
    ],
    "meaning": "time, hour",
    "onyomiWords": [
      {
        "word": "時間",
        "reading": "じかん",
        "meaning": "time, hours"
      },
      {
        "word": "時差",
        "reading": "じさ",
        "meaning": "time difference"
      },
      {
        "word": "時間割 ",
        "reading": "じかんわり",
        "meaning": "timetable"
      }
    ],
    "kunyomiWords": [
      {
        "word": "時折",
        "reading": "ときおり",
        "meaning": "sometimes"
      }
    ],
    "specialReadings": [],
    "examples": [
      {
        "sentence": "1. 今何時ですか？",
        "reading": "いまなんじですか？",
        "romanji": "ima nanji desu ka?",
        "meaning": "What time is it now?"
      },
      {
        "sentence": "2. そこでは冬には時々雪が降る。",
        "reading": "そこではふゆにはときどきゆきがふる。",
        "romanji": "soko de wa fuyu ni wa tokidoki yuki ga furu.",
        "meaning": "Sometimes it snows there in winter."
      },
      {
        "sentence": "3. 私は毎日３時間勉強します。",
        "reading": "わたしはまいにち３じかんべんきょうします。",
        "romanji": "watashi wa mainichi 3 jikan benkyou shimasu.",
        "meaning": "I study for 3 hours every day."
      }
    ]
  },
  "行": {
    "onyomi": [
      "コウ","ギョウ","アン"
    ],
    "kunyomi": [
      "い(く)","ゆ(く)","おこな(う)"
    ],
    "meaning": "going, journey, carry out, line, row",
    "onyomiWords": [
      {
        "word": "銀行",
        "reading": "ぎんこう",
        "meaning": "bank"
      },
      {
        "word": "行列",
        "reading": "ぎょうれつ",
        "meaning": "line, queue"
      },
      {
        "word": "犯行",
        "reading": "はんこう",
        "meaning": "crime, criminal act"
      }
    ],
    "kunyomiWords": [
      {
        "word": "行く先",
        "reading": "ゆくさき",
        "meaning": "destination, whereabouts, future, prospects"
      }
    ],
    "specialReadings": [
      {
        "word": "流行",
        "reading": "はやり",
        "meaning": "fashion"
      }
    ],
    "examples": [
      {
        "sentence": "1. 来週の水曜日にそちらへ行く。",
        "reading": "らいしゅうのすいようびにそちらへいく。",
        "romanji": "raishuu no suiyoubi ni sochira he iku.",
        "meaning": "I'll go over there next Wednesday."
      },
      {
        "sentence": "2. 毎年旅行したい。",
        "reading": "まいとしりょこうしたい。",
        "romanji": "maitoshi ryokou shitai.",
        "meaning": "I want to travel every year."
      },
      {
        "sentence": "3. どの銀行を利用していますか？",
        "reading": "どのぎんこうをりようしていますか？",
        "romanji": "dono ginkou o riyou shiteimasu ka?",
        "meaning": "Which bank do you use?"
      }
    ]
  },
  "見": {
    "onyomi": [
      "ケン"
    ],
    "kunyomi": [
      "み(る)","み(せる)"
    ],
    "meaning": "see, hopes, chances, idea, opinion, look at, visible",
    "onyomiWords": [
      {
        "word": "拝見",
        "reading": "はいけん",
        "meaning": "seeing, look at"
      },
      {
        "word": "見物",
        "reading": "けんぶつ",
        "meaning": "sightseeing"
      },
      {
        "word": "会見",
        "reading": "かいけん",
        "meaning": "interview, audience"
      }
    ],
    "kunyomiWords": [
      {
        "word": "見方",
        "reading": "みかた",
        "meaning": "point of view"
      }
    ],
    "specialReadings": [],
    "examples": [
      {
        "sentence": "1. この映画を見たことありますか？",
        "reading": "このえいがをみたことありますか？",
        "romanji": "kono eiga o mita koto arimasu ka?",
        "meaning": "Have you seen this movie before?"
      },
      {
        "sentence": "2. 家から学校が見える。",
        "reading": "いえからがっこうがみえる。",
        "romanji": "ie kara gakkou ga mieru.",
        "meaning": "I can see my school from my house."
      },
      {
        "sentence": "3. 来週の花見は楽しみです。",
        "reading": "らいしゅうのはなみはたのしみです。",
        "romanji": "raishuu no hanami wa tanoshimi desu.",
        "meaning": "I'm really looking forward to the flower viewing next week."
      }
    ]
  },
  "月": {
    "onyomi": [
      "ゲツ","ガツ"
    ],
    "kunyomi": [
      "つき"
    ],
    "meaning": "month, moon",
    "onyomiWords": [
      {
        "word": "月末",
        "reading": "げつまつ",
        "meaning": "end of the month"
      },
      {
        "word": "満月",
        "reading": "まんげつ",
        "meaning": "full moon"
      },
      {
        "word": "旧正月",
        "reading": "きゅうしょうがつ",
        "meaning": "lunar New Year (esp. the Chinese New Year)"
      }
    ],
    "kunyomiWords": [
      {
        "word": "毎月",
        "reading": "まいつき",
        "meaning": "every month"
      }
    ],
    "specialReadings": [],
    "examples": [
      {
        "sentence": "1. 今月は日本に行きます。",
        "reading": "こんげつはにほんにいきます。",
        "romanji": "kongetsu wa nihon ni ikimasu.",
        "meaning": "I'm going to Japan this month."
      },
      {
        "sentence": "2. 私は9月に生まれました。",
        "reading": "わたしはくがつにうまれました。",
        "romanji": "watashi wa kugatsu ni umaremashita.",
        "meaning": "I was born in September."
      },
      {
        "sentence": "3. 私はハイキングに毎月行ってます。",
        "reading": "わたしはハイキングにまいつきいっています。",
        "romanji": "watashi wa haikingu ni maitsuki itteimasu.",
        "meaning": "I go hiking every month."
      }
    ]
  },
  "分": {
    "onyomi": [
      "ブン","フン","ブ"
    ],
    "kunyomi": [
      "わ(ける)"
    ],
    "meaning": "part, minute of time, understand",
    "onyomiWords": [
      {
        "word": "毎分",
        "reading": "まいふん",
        "meaning": "every minute, per minute"
      },
      {
        "word": "多分",
        "reading": "たぶん",
        "meaning": "perhaps; probably"
      },
      {
        "word": "水分",
        "reading": "すいぶん",
        "meaning": "water; liquid; fluid; moisture"
      }
    ],
    "kunyomiWords": [
      {
        "word": "引き分け",
        "reading": "ひきわけ",
        "meaning": "draw (in competition); tie game"
      }
    ],
    "specialReadings": [],
    "examples": [
      {
        "sentence": "1. 日本語分かりません。",
        "reading": "にほんごわかりません。",
        "romanji": "nihongo wakarimasen.",
        "meaning": "I don't understand Japanese."
      },
      {
        "sentence": "2. 今日は気分はどうですか？",
        "reading": "きょうはきぶんはどうですか？",
        "romanji": "kyou wa kibun wa dou desu ka?",
        "meaning": "How are you feeling today?"
      },
      {
        "sentence": "3. この本はほとんど半分読んだ。",
        "reading": "このほんはほとんどはんぶんよんだ。",
        "romanji": "kono hon wa hotondo hanbun yonda.",
        "meaning": "I've read about half of this book."
      }
    ]
  },
  "後": {
    "onyomi": [
      "コク"
    ],
    "kunyomi": [
      "くに"
    ],
    "meaning": "country",
    "onyomiWords": [
      {
        "word": "国王",
        "reading": "こくおう",
        "meaning": "King"
      },
      {
        "word": "韓国",
        "reading": "かんこく",
        "meaning": "South Korea"
      },
      {
        "word": "中国",
        "reading": "ちゅうごく",
        "meaning": "China"
      },
      {
        "word": "米国",
        "reading": "べいこく",
        "meaning": "America, USA"
      },
      {
        "word": "外国",
        "reading": "がいこく",
        "meaning": "foreign country"
      },
      {
        "word": "国際",
        "reading": "こくさい",
        "meaning": "international"
      },
      {
        "word": "外国人",
        "reading": "がいこくじん",
        "meaning": "foreigner, foreign citizen"
      }
    ],
    "kunyomiWords": [
      {
        "word": "国",
        "reading": "くに",
        "meaning": "country, state, region, national government"
      }
    ],
    "specialReadings": [],
    "examples": [
      {
        "sentence": "1. あなたはどこの国から来ましたか？",
        "reading": "あなたはどこのくにからきましたか？",
        "romanji": "anata wa doko no kuni kara kimashita ka?",
        "meaning": "What country did you come from?"
      },
      {
        "sentence": "2. 彼は外国に長年住んでいた。",
        "reading": "かれはがいこくにながねんすんでいた。",
        "romanji": "kare wa gaikoku ni naganen sundeita.",
        "meaning": "He lived abroad for many years."
      },
      {
        "sentence": "3. 私は米国から来ました。",
        "reading": "わたしはべいこくからきました。",
        "romanji": "watashi wa beikoku kara kimashita.",
        "meaning": "I came here from the USA."
      }
    ]
  },
  "前": {
    "onyomi": [
      "コク"
    ],
    "kunyomi": [
      "くに"
    ],
    "meaning": "country",
    "onyomiWords": [
      {
        "word": "国王",
        "reading": "こくおう",
        "meaning": "King"
      },
      {
        "word": "韓国",
        "reading": "かんこく",
        "meaning": "South Korea"
      },
      {
        "word": "中国",
        "reading": "ちゅうごく",
        "meaning": "China"
      },
      {
        "word": "米国",
        "reading": "べいこく",
        "meaning": "America, USA"
      },
      {
        "word": "外国",
        "reading": "がいこく",
        "meaning": "foreign country"
      },
      {
        "word": "国際",
        "reading": "こくさい",
        "meaning": "international"
      },
      {
        "word": "外国人",
        "reading": "がいこくじん",
        "meaning": "foreigner, foreign citizen"
      }
    ],
    "kunyomiWords": [
      {
        "word": "国人一倍",
        "reading": "ひといちばい",
        "meaning": "(much) more than others, exceedingly"
      }
    ],
    "specialReadings": [],
    "examples": [
      {
        "sentence": "1. あなたはどこの国から来ましたか？",
        "reading": "あなたはどこのくにからきましたか？",
        "romanji": "anata wa doko no kuni kara kimashita ka?",
        "meaning": "What country did you come from?"
      },
      {
        "sentence": "2. 彼は外国に長年住んでいた。",
        "reading": "かれはがいこくにながねんすんでいた。",
        "romanji": "kare wa gaikoku ni naganen sundeita.",
        "meaning": "He lived abroad for many years."
      },
      {
        "sentence": "3. 私は米国から来ました。",
        "reading": "わたしはべいこくからきました。",
        "romanji": "watashi wa beikoku kara kimashita.",
        "meaning": "I came here from the USA."
      }
    ]
  },
  "生": {
    "onyomi": [
      "コク"
    ],
    "kunyomi": [
      "くに"
    ],
    "meaning": "country",
    "onyomiWords": [
      {
        "word": "国王",
        "reading": "こくおう",
        "meaning": "King"
      },
      {
        "word": "韓国",
        "reading": "かんこく",
        "meaning": "South Korea"
      },
      {
        "word": "中国",
        "reading": "ちゅうごく",
        "meaning": "China"
      },
      {
        "word": "米国",
        "reading": "べいこく",
        "meaning": "America, USA"
      },
      {
        "word": "外国",
        "reading": "がいこく",
        "meaning": "foreign country"
      },
      {
        "word": "国際",
        "reading": "こくさい",
        "meaning": "international"
      },
      {
        "word": "外国人",
        "reading": "がいこくじん",
        "meaning": "foreigner, foreign citizen"
      }
    ],
    "kunyomiWords": [
      {
        "word": "国",
        "reading": "くに",
        "meaning": "country, state, region, national government"
      }
    ],
    "specialReadings": [],
    "examples": [
      {
        "sentence": "1. あなたはどこの国から来ましたか？",
        "reading": "あなたはどこのくにからきましたか？",
        "romanji": "anata wa doko no kuni kara kimashita ka?",
        "meaning": "What country did you come from?"
      },
      {
        "sentence": "2. 彼は外国に長年住んでいた。",
        "reading": "かれはがいこくにながねんすんでいた。",
        "romanji": "kare wa gaikoku ni naganen sundeita.",
        "meaning": "He lived abroad for many years."
      },
      {
        "sentence": "3. 私は米国から来ました。",
        "reading": "わたしはべいこくからきました。",
        "romanji": "watashi wa beikoku kara kimashita.",
        "meaning": "I came here from the USA."
      }
    ]
  },
  "五": {
    "onyomi": [
      "コク"
    ],
    "kunyomi": [
      "くに"
    ],
    "meaning": "country",
    "onyomiWords": [
      {
        "word": "国王",
        "reading": "こくおう",
        "meaning": "King"
      },
      {
        "word": "韓国",
        "reading": "かんこく",
        "meaning": "South Korea"
      },
      {
        "word": "中国",
        "reading": "ちゅうごく",
        "meaning": "China"
      },
      {
        "word": "米国",
        "reading": "べいこく",
        "meaning": "America, USA"
      },
      {
        "word": "外国",
        "reading": "がいこく",
        "meaning": "foreign country"
      },
      {
        "word": "国際",
        "reading": "こくさい",
        "meaning": "international"
      },
      {
        "word": "外国人",
        "reading": "がいこくじん",
        "meaning": "foreigner, foreign citizen"
      }
    ],
    "kunyomiWords": [
      {
        "word": "国",
        "reading": "くに",
        "meaning": "country, state, region, national government"
      }
    ],
    "specialReadings": [],
    "examples": [
      {
        "sentence": "1. あなたはどこの国から来ましたか？",
        "reading": "あなたはどこのくにからきましたか？",
        "romanji": "anata wa doko no kuni kara kimashita ka?",
        "meaning": "What country did you come from?"
      },
      {
        "sentence": "2. 彼は外国に長年住んでいた。",
        "reading": "かれはがいこくにながねんすんでいた。",
        "romanji": "kare wa gaikoku ni naganen sundeita.",
        "meaning": "He lived abroad for many years."
      },
      {
        "sentence": "3. 私は米国から来ました。",
        "reading": "わたしはべいこくからきました。",
        "romanji": "watashi wa beikoku kara kimashita.",
        "meaning": "I came here from the USA."
      }
    ]
  },
  "間": {
    "onyomi": [
      "コク"
    ],
    "kunyomi": [
      "くに"
    ],
    "meaning": "country",
    "onyomiWords": [
      {
        "word": "国王",
        "reading": "こくおう",
        "meaning": "King"
      },
      {
        "word": "韓国",
        "reading": "かんこく",
        "meaning": "South Korea"
      },
      {
        "word": "中国",
        "reading": "ちゅうごく",
        "meaning": "China"
      },
      {
        "word": "米国",
        "reading": "べいこく",
        "meaning": "America, USA"
      },
      {
        "word": "外国",
        "reading": "がいこく",
        "meaning": "foreign country"
      },
      {
        "word": "国際",
        "reading": "こくさい",
        "meaning": "international"
      },
      {
        "word": "外国人",
        "reading": "がいこくじん",
        "meaning": "foreigner, foreign citizen"
      }
    ],
    "kunyomiWords": [
      {
        "word": "国",
        "reading": "くに",
        "meaning": "country, state, region, national government"
      }
    ],
    "specialReadings": [],
    "examples": [
      {
        "sentence": "1. あなたはどこの国から来ましたか？",
        "reading": "あなたはどこのくにからきましたか？",
        "romanji": "anata wa doko no kuni kara kimashita ka?",
        "meaning": "What country did you come from?"
      },
      {
        "sentence": "2. 彼は外国に長年住んでいた。",
        "reading": "かれはがいこくにながねんすんでいた。",
        "romanji": "kare wa gaikoku ni naganen sundeita.",
        "meaning": "He lived abroad for many years."
      },
      {
        "sentence": "3. 私は米国から来ました。",
        "reading": "わたしはべいこくからきました。",
        "romanji": "watashi wa beikoku kara kimashita.",
        "meaning": "I came here from the USA."
      }
    ]
  },
  "上": {
    "onyomi": [
      "コク"
    ],
    "kunyomi": [
      "くに"
    ],
    "meaning": "country",
    "onyomiWords": [
      {
        "word": "国王",
        "reading": "こくおう",
        "meaning": "King"
      },
      {
        "word": "韓国",
        "reading": "かんこく",
        "meaning": "South Korea"
      },
      {
        "word": "中国",
        "reading": "ちゅうごく",
        "meaning": "China"
      },
      {
        "word": "米国",
        "reading": "べいこく",
        "meaning": "America, USA"
      },
      {
        "word": "外国",
        "reading": "がいこく",
        "meaning": "foreign country"
      },
      {
        "word": "国際",
        "reading": "こくさい",
        "meaning": "international"
      },
      {
        "word": "外国人",
        "reading": "がいこくじん",
        "meaning": "foreigner, foreign citizen"
      }
    ],
    "kunyomiWords": [
      {
        "word": "国",
        "reading": "くに",
        "meaning": "country, state, region, national government"
      }
    ],
    "specialReadings": [],
    "examples": [
      {
        "sentence": "1. あなたはどこの国から来ましたか？",
        "reading": "あなたはどこのくにからきましたか？",
        "romanji": "anata wa doko no kuni kara kimashita ka?",
        "meaning": "What country did you come from?"
      },
      {
        "sentence": "2. 彼は外国に長年住んでいた。",
        "reading": "かれはがいこくにながねんすんでいた。",
        "romanji": "kare wa gaikoku ni naganen sundeita.",
        "meaning": "He lived abroad for many years."
      },
      {
        "sentence": "3. 私は米国から来ました。",
        "reading": "わたしはべいこくからきました。",
        "romanji": "watashi wa beikoku kara kimashita.",
        "meaning": "I came here from the USA."
      }
    ]
  }
}